<?xml version="1.0" encoding="UTF-8"?>
<FDSNStationXML xmlns="http://www.fdsn.org/xml/station/1" schemaVersion="1">
    <Source>CTBTO</Source>
    <Created>2026-04-14T00:00:00</Created>
    <Network code="IM" startDate="2005-04-14T15:28:02" endDate="2050-12-31T23:59:59">
        <TotalNumberStations>12</TotalNumberStations>
        <Station code="I50H1" startDate="2005-04-14T15:28:02" endDate="2050-12-31T23:59:59">
            <Latitude>-7.936778</Latitude>
            <Longitude>-14.375301</Longitude>
            <Elevation>0.181747</Elevation>
            <Site>
                <Name>I50GB ASCENSION ISLAND UK INFRASONIC ARRAY H1</Name>
            </Site>
            <Channel code="BDF" locationCode="" startDate="2018-05-02T00:00:00" endDate="2050-12-31T23:59:59">
                <Sensor>
                    <Description>I50GB ASCENSION ISLAND UK INFRASONIC ARRAY</Description>
                </Sensor>
                <Latitude>-7.936778</Latitude>
                <Longitude>-14.375301</Longitude>
                <Elevation>0.181747</Elevation>
                <Depth>0</Depth>
                <Azimuth>0</Azimuth>
                <Dip>0</Dip>
                <SampleRate>20</SampleRate>
                <Response>
                    <InstrumentSensitivity>
                        <Value>10485.8</Value>
                        <Frequency>0.1</Frequency>
                        <InputUnits>
                            <Name>PA</Name>
                        </InputUnits>
                        <OutputUnits>
                            <Name>COUNTS</Name>
                        </OutputUnits>
                    </InstrumentSensitivity>
                </Response>
            </Channel>
            <Channel code="BDF" locationCode="" startDate="2017-10-12T00:00:00" endDate="2018-05-02T00:00:00">
                <Sensor>
                    <Description>I50GB ASCENSION ISLAND UK INFRASONIC ARRAY</Description>
                </Sensor>
                <Latitude>-7.936780</Latitude>
                <Longitude>-14.375300</Longitude>
                <Elevation>0.18412</Elevation>
                <Depth>0</Depth>
                <Azimuth>0</Azimuth>
                <Dip>0</Dip>
                <SampleRate>20</SampleRate>
                <Response>
                    <InstrumentSensitivity>
                        <Value>10485.8</Value>
                        <Frequency>0.1</Frequency>
                        <InputUnits>
                            <Name>PA</Name>
                        </InputUnits>
                        <OutputUnits>
                            <Name>COUNTS</Name>
                        </OutputUnits>
                    </InstrumentSensitivity>
                </Response>
            </Channel>
            <Channel code="BDF" locationCode="" startDate="2005-04-14T15:28:02" endDate="2017-10-12T00:00:00">
                <Sensor>
                    <Description>I50GB ASCENSION ISLAND UK INFRASONIC ARRAY</Description>
                </Sensor>
                <Latitude>-7.936780</Latitude>
                <Longitude>-14.375300</Longitude>
                <Elevation>0.18412</Elevation>
                <Depth>0</Depth>
                <Azimuth>0</Azimuth>
                <Dip>0</Dip>
                <SampleRate>20</SampleRate>
                <Response>
                    <InstrumentSensitivity>
                        <Value>10485.8</Value>
                        <Frequency>0.1</Frequency>
                        <InputUnits>
                            <Name>PA</Name>
                        </InputUnits>
                        <OutputUnits>
                            <Name>COUNTS</Name>
                        </OutputUnits>
                    </InstrumentSensitivity>
                </Response>
            </Channel>
            <Channel code="BDF" locationCode="" startDate="2005-04-14T15:28:02" endDate="2017-10-11T00:00:00">
                <Sensor>
                    <Description>I50GB ASCENSION ISLAND UK INFRASONIC ARRAY</Description>
                </Sensor>
                <Latitude>-7.936800</Latitude>
                <Longitude>-14.375300</Longitude>
                <Elevation>184.1</Elevation>
                <Depth>0</Depth>
                <Azimuth>0</Azimuth>
                <Dip>0</Dip>
                <SampleRate>20</SampleRate>
                <Response>
                    <InstrumentSensitivity>
                        <Value>10526.3</Value>
                        <Frequency>0.1</Frequency>
                        <InputUnits>
                            <Name>PA</Name>
                        </InputUnits>
                        <OutputUnits>
                            <Name>COUNTS</Name>
                        </OutputUnits>
                    </InstrumentSensitivity>
                </Response>
            </Channel>
            <Channel code="BDF" locationCode="" startDate="2017-10-12T00:00:00" endDate="2018-02-21T00:00:00">
                <Sensor>
                    <Description>I50GB ASCENSION ISLAND UK INFRASONIC ARRAY</Description>
                </Sensor>
                <Latitude>-7.936800</Latitude>
                <Longitude>-14.375300</Longitude>
                <Elevation>184.1</Elevation>
                <Depth>0</Depth>
                <Azimuth>0</Azimuth>
                <Dip>0</Dip>
                <SampleRate>20</SampleRate>
                <Response>
                    <InstrumentSensitivity>
                        <Value>10526.3</Value>
                        <Frequency>0.1</Frequency>
                        <InputUnits>
                            <Name>PA</Name>
                        </InputUnits>
                        <OutputUnits>
                            <Name>COUNTS</Name>
                        </OutputUnits>
                    </InstrumentSensitivity>
                </Response>
            </Channel>
            <Channel code="BDF" locationCode="" startDate="2018-02-22T00:00:00" endDate="2050-12-31T23:59:59">
                <Sensor>
                    <Description>I50GB ASCENSION ISLAND UK INFRASONIC ARRAY</Description>
                </Sensor>
                <Latitude>-7.936800</Latitude>
                <Longitude>-14.375300</Longitude>
                <Elevation>181.7</Elevation>
                <Depth>0</Depth>
                <Azimuth>0</Azimuth>
                <Dip>0</Dip>
                <SampleRate>20</SampleRate>
                <Response>
                    <InstrumentSensitivity>
                        <Value>10526.3</Value>
                        <Frequency>0.1</Frequency>
                        <InputUnits>
                            <Name>PA</Name>
                        </InputUnits>
                        <OutputUnits>
                            <Name>COUNTS</Name>
                        </OutputUnits>
                    </InstrumentSensitivity>
                </Response>
            </Channel>
        </Station>
        <Station code="I50H2" startDate="2005-04-14T15:28:02" endDate="2050-12-31T23:59:59">
            <Latitude>-7.938876</Latitude>
            <Longitude>-14.374064</Longitude>
            <Elevation>0.195703</Elevation>
            <Site>
                <Name>I50GB ASCENSION ISLAND UK INFRASONIC ARRAY H2</Name>
            </Site>
            <Channel code="BDF" locationCode="" startDate="2018-05-02T00:00:00" endDate="2050-12-31T23:59:59">
                <Sensor>
                    <Description>I50GB ASCENSION ISLAND UK INFRASONIC ARRAY</Description>
                </Sensor>
                <Latitude>-7.938876</Latitude>
                <Longitude>-14.374064</Longitude>
                <Elevation>0.195703</Elevation>
                <Depth>0</Depth>
                <Azimuth>0</Azimuth>
                <Dip>0</Dip>
                <SampleRate>20</SampleRate>
                <Response>
                    <InstrumentSensitivity>
                        <Value>10485.8</Value>
                        <Frequency>0.1</Frequency>
                        <InputUnits>
                            <Name>PA</Name>
                        </InputUnits>
                        <OutputUnits>
                            <Name>COUNTS</Name>
                        </OutputUnits>
                    </InstrumentSensitivity>
                </Response>
            </Channel>
            <Channel code="BDF" locationCode="" startDate="2017-10-12T00:00:00" endDate="2018-05-02T00:00:00">
                <Sensor>
                    <Description>I50GB ASCENSION ISLAND UK INFRASONIC ARRAY</Description>
                </Sensor>
                <Latitude>-7.938880</Latitude>
                <Longitude>-14.374060</Longitude>
                <Elevation>0.19808</Elevation>
                <Depth>0</Depth>
                <Azimuth>0</Azimuth>
                <Dip>0</Dip>
                <SampleRate>20</SampleRate>
                <Response>
                    <InstrumentSensitivity>
                        <Value>10485.8</Value>
                        <Frequency>0.1</Frequency>
                        <InputUnits>
                            <Name>PA</Name>
                        </InputUnits>
                        <OutputUnits>
                            <Name>COUNTS</Name>
                        </OutputUnits>
                    </InstrumentSensitivity>
                </Response>
            </Channel>
            <Channel code="BDF" locationCode="" startDate="2005-04-14T15:28:02" endDate="2017-10-12T00:00:00">
                <Sensor>
                    <Description>I50GB ASCENSION ISLAND UK INFRASONIC ARRAY</Description>
                </Sensor>
                <Latitude>-7.938880</Latitude>
                <Longitude>-14.374060</Longitude>
                <Elevation>0.19808</Elevation>
                <Depth>0</Depth>
                <Azimuth>0</Azimuth>
                <Dip>0</Dip>
                <SampleRate>20</SampleRate>
                <Response>
                    <InstrumentSensitivity>
                        <Value>10485.8</Value>
                        <Frequency>0.1</Frequency>
                        <InputUnits>
                            <Name>PA</Name>
                        </InputUnits>
                        <OutputUnits>
                            <Name>COUNTS</Name>
                        </OutputUnits>
                    </InstrumentSensitivity>
                </Response>
            </Channel>
            <Channel code="BDF" locationCode="" startDate="2005-04-14T15:28:02" endDate="2017-10-11T00:00:00">
                <Sensor>
                    <Description>I50GB ASCENSION ISLAND UK INFRASONIC ARRAY</Description>
                </Sensor>
                <Latitude>-7.938900</Latitude>
                <Longitude>-14.374100</Longitude>
                <Elevation>198.1</Elevation>
                <Depth>0</Depth>
                <Azimuth>0</Azimuth>
                <Dip>0</Dip>
                <SampleRate>20</SampleRate>
                <Response>
                    <InstrumentSensitivity>
                        <Value>10526.3</Value>
                        <Frequency>0.1</Frequency>
                        <InputUnits>
                            <Name>PA</Name>
                        </InputUnits>
                        <OutputUnits>
                            <Name>COUNTS</Name>
                        </OutputUnits>
                    </InstrumentSensitivity>
                </Response>
            </Channel>
            <Channel code="BDF" locationCode="" startDate="2017-10-12T00:00:00" endDate="2018-02-21T00:00:00">
                <Sensor>
                    <Description>I50GB ASCENSION ISLAND UK INFRASONIC ARRAY</Description>
                </Sensor>
                <Latitude>-7.938900</Latitude>
                <Longitude>-14.374100</Longitude>
                <Elevation>198.1</Elevation>
                <Depth>0</Depth>
                <Azimuth>0</Azimuth>
                <Dip>0</Dip>
                <SampleRate>20</SampleRate>
                <Response>
                    <InstrumentSensitivity>
                        <Value>10526.3</Value>
                        <Frequency>0.1</Frequency>
                        <InputUnits>
                            <Name>PA</Name>
                        </InputUnits>
                        <OutputUnits>
                            <Name>COUNTS</Name>
                        </OutputUnits>
                    </InstrumentSensitivity>
                </Response>
            </Channel>
            <Channel code="BDF" locationCode="" startDate="2018-02-22T00:00:00" endDate="2050-12-31T23:59:59">
                <Sensor>
                    <Description>I50GB ASCENSION ISLAND UK INFRASONIC ARRAY</Description>
                </Sensor>
                <Latitude>-7.938900</Latitude>
                <Longitude>-14.374100</Longitude>
                <Elevation>195.7</Elevation>
                <Depth>0</Depth>
                <Azimuth>0</Azimuth>
                <Dip>0</Dip>
                <SampleRate>20</SampleRate>
                <Response>
                    <InstrumentSensitivity>
                        <Value>10526.3</Value>
                        <Frequency>0.1</Frequency>
                        <InputUnits>
                            <Name>PA</Name>
                        </InputUnits>
                        <OutputUnits>
                            <Name>COUNTS</Name>
                        </OutputUnits>
                    </InstrumentSensitivity>
                </Response>
            </Channel>
        </Station>
        <Station code="I50H3" startDate="2005-04-14T15:28:02" endDate="2050-12-31T23:59:59">
            <Latitude>-7.939561</Latitude>
            <Longitude>-14.376625</Longitude>
            <Elevation>0.177477</Elevation>
            <Site>
                <Name>I50GB ASCENSION ISLAND UK INFRASONIC ARRAY H3</Name>
            </Site>
            <Channel code="BDF" locationCode="" startDate="2018-05-02T00:00:00" endDate="2050-12-31T23:59:59">
                <Sensor>
                    <Description>I50GB ASCENSION ISLAND UK INFRASONIC ARRAY</Description>
                </Sensor>
                <Latitude>-7.939561</Latitude>
                <Longitude>-14.376625</Longitude>
                <Elevation>0.177477</Elevation>
                <Depth>0</Depth>
                <Azimuth>0</Azimuth>
                <Dip>0</Dip>
                <SampleRate>20</SampleRate>
                <Response>
                    <InstrumentSensitivity>
                        <Value>10485.8</Value>
                        <Frequency>0.1</Frequency>
                        <InputUnits>
                            <Name>PA</Name>
                        </InputUnits>
                        <OutputUnits>
                            <Name>COUNTS</Name>
                        </OutputUnits>
                    </InstrumentSensitivity>
                </Response>
            </Channel>
            <Channel code="BDF" locationCode="" startDate="2017-10-12T00:00:00" endDate="2018-05-02T00:00:00">
                <Sensor>
                    <Description>I50GB ASCENSION ISLAND UK INFRASONIC ARRAY</Description>
                </Sensor>
                <Latitude>-7.939560</Latitude>
                <Longitude>-14.376620</Longitude>
                <Elevation>0.17986</Elevation>
                <Depth>0</Depth>
                <Azimuth>0</Azimuth>
                <Dip>0</Dip>
                <SampleRate>20</SampleRate>
                <Response>
                    <InstrumentSensitivity>
                        <Value>10485.8</Value>
                        <Frequency>0.1</Frequency>
                        <InputUnits>
                            <Name>PA</Name>
                        </InputUnits>
                        <OutputUnits>
                            <Name>COUNTS</Name>
                        </OutputUnits>
                    </InstrumentSensitivity>
                </Response>
            </Channel>
            <Channel code="BDF" locationCode="" startDate="2005-04-14T15:28:02" endDate="2017-10-12T00:00:00">
                <Sensor>
                    <Description>I50GB ASCENSION ISLAND UK INFRASONIC ARRAY</Description>
                </Sensor>
                <Latitude>-7.939560</Latitude>
                <Longitude>-14.376620</Longitude>
                <Elevation>0.17986</Elevation>
                <Depth>0</Depth>
                <Azimuth>0</Azimuth>
                <Dip>0</Dip>
                <SampleRate>20</SampleRate>
                <Response>
                    <InstrumentSensitivity>
                        <Value>10485.8</Value>
                        <Frequency>0.1</Frequency>
                        <InputUnits>
                            <Name>PA</Name>
                        </InputUnits>
                        <OutputUnits>
                            <Name>COUNTS</Name>
                        </OutputUnits>
                    </InstrumentSensitivity>
                </Response>
            </Channel>
            <Channel code="BDF" locationCode="" startDate="2005-04-14T15:28:02" endDate="2017-10-11T00:00:00">
                <Sensor>
                    <Description>I50GB ASCENSION ISLAND UK INFRASONIC ARRAY</Description>
                </Sensor>
                <Latitude>-7.939600</Latitude>
                <Longitude>-14.376600</Longitude>
                <Elevation>179.9</Elevation>
                <Depth>0</Depth>
                <Azimuth>0</Azimuth>
                <Dip>0</Dip>
                <SampleRate>20</SampleRate>
                <Response>
                    <InstrumentSensitivity>
                        <Value>10526.3</Value>
                        <Frequency>0.1</Frequency>
                        <InputUnits>
                            <Name>PA</Name>
                        </InputUnits>
                        <OutputUnits>
                            <Name>COUNTS</Name>
                        </OutputUnits>
                    </InstrumentSensitivity>
                </Response>
            </Channel>
            <Channel code="BDF" locationCode="" startDate="2017-10-12T00:00:00" endDate="2018-02-21T00:00:00">
                <Sensor>
                    <Description>I50GB ASCENSION ISLAND UK INFRASONIC ARRAY</Description>
                </Sensor>
                <Latitude>-7.939600</Latitude>
                <Longitude>-14.376600</Longitude>
                <Elevation>179.9</Elevation>
                <Depth>0</Depth>
                <Azimuth>0</Azimuth>
                <Dip>0</Dip>
                <SampleRate>20</SampleRate>
                <Response>
                    <InstrumentSensitivity>
                        <Value>10526.3</Value>
                        <Frequency>0.1</Frequency>
                        <InputUnits>
                            <Name>PA</Name>
                        </InputUnits>
                        <OutputUnits>
                            <Name>COUNTS</Name>
                        </OutputUnits>
                    </InstrumentSensitivity>
                </Response>
            </Channel>
            <Channel code="BDF" locationCode="" startDate="2018-02-22T00:00:00" endDate="2050-12-31T23:59:59">
                <Sensor>
                    <Description>I50GB ASCENSION ISLAND UK INFRASONIC ARRAY</Description>
                </Sensor>
                <Latitude>-7.939600</Latitude>
                <Longitude>-14.376600</Longitude>
                <Elevation>177.5</Elevation>
                <Depth>0</Depth>
                <Azimuth>0</Azimuth>
                <Dip>0</Dip>
                <SampleRate>20</SampleRate>
                <Response>
                    <InstrumentSensitivity>
                        <Value>10526.3</Value>
                        <Frequency>0.1</Frequency>
                        <InputUnits>
                            <Name>PA</Name>
                        </InputUnits>
                        <OutputUnits>
                            <Name>COUNTS</Name>
                        </OutputUnits>
                    </InstrumentSensitivity>
                </Response>
            </Channel>
        </Station>
        <Station code="I50H4" startDate="2005-04-14T15:28:02" endDate="2050-12-31T23:59:59">
            <Latitude>-7.937121</Latitude>
            <Longitude>-14.377054</Longitude>
            <Elevation>0.172233</Elevation>
            <Site>
                <Name>I50GB ASCENSION ISLAND UK INFRASONIC ARRAY H4</Name>
            </Site>
            <Channel code="BDF" locationCode="" startDate="2018-05-02T00:00:00" endDate="2050-12-31T23:59:59">
                <Sensor>
                    <Description>I50GB ASCENSION ISLAND UK INFRASONIC ARRAY</Description>
                </Sensor>
                <Latitude>-7.937121</Latitude>
                <Longitude>-14.377054</Longitude>
                <Elevation>0.172233</Elevation>
                <Depth>0</Depth>
                <Azimuth>0</Azimuth>
                <Dip>0</Dip>
                <SampleRate>20</SampleRate>
                <Response>
                    <InstrumentSensitivity>
                        <Value>10485.8</Value>
                        <Frequency>0.1</Frequency>
                        <InputUnits>
                            <Name>PA</Name>
                        </InputUnits>
                        <OutputUnits>
                            <Name>COUNTS</Name>
                        </OutputUnits>
                    </InstrumentSensitivity>
                </Response>
            </Channel>
            <Channel code="BDF" locationCode="" startDate="2017-10-12T00:00:00" endDate="2018-05-02T00:00:00">
                <Sensor>
                    <Description>I50GB ASCENSION ISLAND UK INFRASONIC ARRAY</Description>
                </Sensor>
                <Latitude>-7.937120</Latitude>
                <Longitude>-14.377050</Longitude>
                <Elevation>0.1746</Elevation>
                <Depth>0</Depth>
                <Azimuth>0</Azimuth>
                <Dip>0</Dip>
                <SampleRate>20</SampleRate>
                <Response>
                    <InstrumentSensitivity>
                        <Value>10485.8</Value>
                        <Frequency>0.1</Frequency>
                        <InputUnits>
                            <Name>PA</Name>
                        </InputUnits>
                        <OutputUnits>
                            <Name>COUNTS</Name>
                        </OutputUnits>
                    </InstrumentSensitivity>
                </Response>
            </Channel>
            <Channel code="BDF" locationCode="" startDate="2005-04-14T15:28:02" endDate="2017-10-12T00:00:00">
                <Sensor>
                    <Description>I50GB ASCENSION ISLAND UK INFRASONIC ARRAY</Description>
                </Sensor>
                <Latitude>-7.937120</Latitude>
                <Longitude>-14.377050</Longitude>
                <Elevation>0.1746</Elevation>
                <Depth>0</Depth>
                <Azimuth>0</Azimuth>
                <Dip>0</Dip>
                <SampleRate>20</SampleRate>
                <Response>
                    <InstrumentSensitivity>
                        <Value>10485.8</Value>
                        <Frequency>0.1</Frequency>
                        <InputUnits>
                            <Name>PA</Name>
                        </InputUnits>
                        <OutputUnits>
                            <Name>COUNTS</Name>
                        </OutputUnits>
                    </InstrumentSensitivity>
                </Response>
            </Channel>
            <Channel code="BDF" locationCode="" startDate="2005-04-14T15:28:02" endDate="2017-10-11T00:00:00">
                <Sensor>
                    <Description>I50GB ASCENSION ISLAND UK INFRASONIC ARRAY</Description>
                </Sensor>
                <Latitude>-7.937100</Latitude>
                <Longitude>-14.377100</Longitude>
                <Elevation>174.6</Elevation>
                <Depth>0</Depth>
                <Azimuth>0</Azimuth>
                <Dip>0</Dip>
                <SampleRate>20</SampleRate>
                <Response>
                    <InstrumentSensitivity>
                        <Value>10526.3</Value>
                        <Frequency>0.1</Frequency>
                        <InputUnits>
                            <Name>PA</Name>
                        </InputUnits>
                        <OutputUnits>
                            <Name>COUNTS</Name>
                        </OutputUnits>
                    </InstrumentSensitivity>
                </Response>
            </Channel>
            <Channel code="BDF" locationCode="" startDate="2017-10-12T00:00:00" endDate="2018-02-21T00:00:00">
                <Sensor>
                    <Description>I50GB ASCENSION ISLAND UK INFRASONIC ARRAY</Description>
                </Sensor>
                <Latitude>-7.937100</Latitude>
                <Longitude>-14.377100</Longitude>
                <Elevation>174.6</Elevation>
                <Depth>0</Depth>
                <Azimuth>0</Azimuth>
                <Dip>0</Dip>
                <SampleRate>20</SampleRate>
                <Response>
                    <InstrumentSensitivity>
                        <Value>10526.3</Value>
                        <Frequency>0.1</Frequency>
                        <InputUnits>
                            <Name>PA</Name>
                        </InputUnits>
                        <OutputUnits>
                            <Name>COUNTS</Name>
                        </OutputUnits>
                    </InstrumentSensitivity>
                </Response>
            </Channel>
            <Channel code="BDF" locationCode="" startDate="2018-02-22T00:00:00" endDate="2050-12-31T23:59:59">
                <Sensor>
                    <Description>I50GB ASCENSION ISLAND UK INFRASONIC ARRAY</Description>
                </Sensor>
                <Latitude>-7.937100</Latitude>
                <Longitude>-14.377100</Longitude>
                <Elevation>172.2</Elevation>
                <Depth>0</Depth>
                <Azimuth>0</Azimuth>
                <Dip>0</Dip>
                <SampleRate>20</SampleRate>
                <Response>
                    <InstrumentSensitivity>
                        <Value>10526.3</Value>
                        <Frequency>0.1</Frequency>
                        <InputUnits>
                            <Name>PA</Name>
                        </InputUnits>
                        <OutputUnits>
                            <Name>COUNTS</Name>
                        </OutputUnits>
                    </InstrumentSensitivity>
                </Response>
            </Channel>
        </Station>
        <Station code="I50H5" startDate="2017-10-12T00:00:00" endDate="2050-12-31T23:59:59">
            <Latitude>-7.937707</Latitude>
            <Longitude>-14.375174</Longitude>
            <Elevation>0.185508</Elevation>
            <Site>
                <Name>I50GB ASCENSION ISLAND UK INFRASONIC ARRAY H5</Name>
            </Site>
            <Channel code="BDF" locationCode="" startDate="2018-05-02T00:00:00" endDate="2050-12-31T23:59:59">
                <Sensor>
                    <Description>I50GB ASCENSION ISLAND UK INFRASONIC ARRAY</Description>
                </Sensor>
                <Latitude>-7.937707</Latitude>
                <Longitude>-14.375174</Longitude>
                <Elevation>0.185508</Elevation>
                <Depth>0</Depth>
                <Azimuth>0</Azimuth>
                <Dip>0</Dip>
                <SampleRate>20</SampleRate>
                <Response>
                    <InstrumentSensitivity>
                        <Value>10485.8</Value>
                        <Frequency>0.1</Frequency>
                        <InputUnits>
                            <Name>PA</Name>
                        </InputUnits>
                        <OutputUnits>
                            <Name>COUNTS</Name>
                        </OutputUnits>
                    </InstrumentSensitivity>
                </Response>
            </Channel>
            <Channel code="BDF" locationCode="" startDate="2017-10-12T00:00:00" endDate="2018-05-02T00:00:00">
                <Sensor>
                    <Description>I50GB ASCENSION ISLAND UK INFRASONIC ARRAY</Description>
                </Sensor>
                <Latitude>-7.937740</Latitude>
                <Longitude>-14.375170</Longitude>
                <Elevation>0.18862</Elevation>
                <Depth>0</Depth>
                <Azimuth>0</Azimuth>
                <Dip>0</Dip>
                <SampleRate>20</SampleRate>
                <Response>
                    <InstrumentSensitivity>
                        <Value>10485.8</Value>
                        <Frequency>0.1</Frequency>
                        <InputUnits>
                            <Name>PA</Name>
                        </InputUnits>
                        <OutputUnits>
                            <Name>COUNTS</Name>
                        </OutputUnits>
                    </InstrumentSensitivity>
                </Response>
            </Channel>
            <Channel code="BDF" locationCode="" startDate="2017-10-12T00:00:00" endDate="2018-02-21T00:00:00">
                <Sensor>
                    <Description>I50GB ASCENSION ISLAND UK INFRASONIC ARRAY</Description>
                </Sensor>
                <Latitude>-7.937700</Latitude>
                <Longitude>-14.375200</Longitude>
                <Elevation>188.6</Elevation>
                <Depth>0</Depth>
                <Azimuth>0</Azimuth>
                <Dip>0</Dip>
                <SampleRate>20</SampleRate>
                <Response>
                    <InstrumentSensitivity>
                        <Value>10526.3</Value>
                        <Frequency>0.1</Frequency>
                        <InputUnits>
                            <Name>PA</Name>
                        </InputUnits>
                        <OutputUnits>
                            <Name>COUNTS</Name>
                        </OutputUnits>
                    </InstrumentSensitivity>
                </Response>
            </Channel>
            <Channel code="BDF" locationCode="" startDate="2018-02-22T00:00:00" endDate="2050-12-31T23:59:59">
                <Sensor>
                    <Description>I50GB ASCENSION ISLAND UK INFRASONIC ARRAY</Description>
                </Sensor>
                <Latitude>-7.937700</Latitude>
                <Longitude>-14.375200</Longitude>
                <Elevation>185.5</Elevation>
                <Depth>0</Depth>
                <Azimuth>0</Azimuth>
                <Dip>0</Dip>
                <SampleRate>20</SampleRate>
                <Response>
                    <InstrumentSensitivity>
                        <Value>10526.3</Value>
                        <Frequency>0.1</Frequency>
                        <InputUnits>
                            <Name>PA</Name>
                        </InputUnits>
                        <OutputUnits>
                            <Name>COUNTS</Name>
                        </OutputUnits>
                    </InstrumentSensitivity>
                </Response>
            </Channel>
        </Station>
        <Station code="I50H6" startDate="2017-10-12T00:00:00" endDate="2050-12-31T23:59:59">
            <Latitude>-7.931884</Latitude>
            <Longitude>-14.382070</Longitude>
            <Elevation>0.144256</Elevation>
            <Site>
                <Name>I50GB ASCENSION ISLAND UK INFRASONIC ARRAY H6</Name>
            </Site>
            <Channel code="BDF" locationCode="" startDate="2018-05-02T00:00:00" endDate="2050-12-31T23:59:59">
                <Sensor>
                    <Description>I50GB ASCENSION ISLAND UK INFRASONIC ARRAY</Description>
                </Sensor>
                <Latitude>-7.931884</Latitude>
                <Longitude>-14.382070</Longitude>
                <Elevation>0.144256</Elevation>
                <Depth>0</Depth>
                <Azimuth>0</Azimuth>
                <Dip>0</Dip>
                <SampleRate>20</SampleRate>
                <Response>
                    <InstrumentSensitivity>
                        <Value>10485.8</Value>
                        <Frequency>0.1</Frequency>
                        <InputUnits>
                            <Name>PA</Name>
                        </InputUnits>
                        <OutputUnits>
                            <Name>COUNTS</Name>
                        </OutputUnits>
                    </InstrumentSensitivity>
                </Response>
            </Channel>
            <Channel code="BDF" locationCode="" startDate="2017-10-12T00:00:00" endDate="2018-05-02T00:00:00">
                <Sensor>
                    <Description>I50GB ASCENSION ISLAND UK INFRASONIC ARRAY</Description>
                </Sensor>
                <Latitude>-7.931900</Latitude>
                <Longitude>-14.382040</Longitude>
                <Elevation>0.14727</Elevation>
                <Depth>0</Depth>
                <Azimuth>0</Azimuth>
                <Dip>0</Dip>
                <SampleRate>20</SampleRate>
                <Response>
                    <InstrumentSensitivity>
                        <Value>10485.8</Value>
                        <Frequency>0.1</Frequency>
                        <InputUnits>
                            <Name>PA</Name>
                        </InputUnits>
                        <OutputUnits>
                            <Name>COUNTS</Name>
                        </OutputUnits>
                    </InstrumentSensitivity>
                </Response>
            </Channel>
            <Channel code="BDF" locationCode="" startDate="2017-10-12T00:00:00" endDate="2018-02-21T00:00:00">
                <Sensor>
                    <Description>I50GB ASCENSION ISLAND UK INFRASONIC ARRAY</Description>
                </Sensor>
                <Latitude>-7.931900</Latitude>
                <Longitude>-14.382000</Longitude>
                <Elevation>147.3</Elevation>
                <Depth>0</Depth>
                <Azimuth>0</Azimuth>
                <Dip>0</Dip>
                <SampleRate>20</SampleRate>
                <Response>
                    <InstrumentSensitivity>
                        <Value>10526.3</Value>
                        <Frequency>0.1</Frequency>
                        <InputUnits>
                            <Name>PA</Name>
                        </InputUnits>
                        <OutputUnits>
                            <Name>COUNTS</Name>
                        </OutputUnits>
                    </InstrumentSensitivity>
                </Response>
            </Channel>
            <Channel code="BDF" locationCode="" startDate="2018-02-22T00:00:00" endDate="2050-12-31T23:59:59">
                <Sensor>
                    <Description>I50GB ASCENSION ISLAND UK INFRASONIC ARRAY</Description>
                </Sensor>
                <Latitude>-7.931900</Latitude>
                <Longitude>-14.382100</Longitude>
                <Elevation>144.3</Elevation>
                <Depth>0</Depth>
                <Azimuth>0</Azimuth>
                <Dip>0</Dip>
                <SampleRate>20</SampleRate>
                <Response>
                    <InstrumentSensitivity>
                        <Value>10526.3</Value>
                        <Frequency>0.1</Frequency>
                        <InputUnits>
                            <Name>PA</Name>
                        </InputUnits>
                        <OutputUnits>
                            <Name>COUNTS</Name>
                        </OutputUnits>
                    </InstrumentSensitivity>
                </Response>
            </Channel>
        </Station>
        <Station code="I50H7" startDate="2017-10-12T00:00:00" endDate="2050-12-31T23:59:59">
            <Latitude>-7.932491</Latitude>
            <Longitude>-14.357241</Longitude>
            <Elevation>0.222861</Elevation>
            <Site>
                <Name>I50GB ASCENSION ISLAND UK INFRASONIC ARRAY H7</Name>
            </Site>
            <Channel code="BDF" locationCode="" startDate="2018-05-02T00:00:00" endDate="2050-12-31T23:59:59">
                <Sensor>
                    <Description>I50GB ASCENSION ISLAND UK INFRASONIC ARRAY</Description>
                </Sensor>
                <Latitude>-7.932491</Latitude>
                <Longitude>-14.357241</Longitude>
                <Elevation>0.222861</Elevation>
                <Depth>0</Depth>
                <Azimuth>0</Azimuth>
                <Dip>0</Dip>
                <SampleRate>20</SampleRate>
                <Response>
                    <InstrumentSensitivity>
                        <Value>10485.8</Value>
                        <Frequency>0.1</Frequency>
                        <InputUnits>
                            <Name>PA</Name>
                        </InputUnits>
                        <OutputUnits>
                            <Name>COUNTS</Name>
                        </OutputUnits>
                    </InstrumentSensitivity>
                </Response>
            </Channel>
            <Channel code="BDF" locationCode="" startDate="2017-10-12T00:00:00" endDate="2018-05-02T00:00:00">
                <Sensor>
                    <Description>I50GB ASCENSION ISLAND UK INFRASONIC ARRAY</Description>
                </Sensor>
                <Latitude>-7.932500</Latitude>
                <Longitude>-14.357210</Longitude>
                <Elevation>0.21797</Elevation>
                <Depth>0</Depth>
                <Azimuth>0</Azimuth>
                <Dip>0</Dip>
                <SampleRate>20</SampleRate>
                <Response>
                    <InstrumentSensitivity>
                        <Value>10485.8</Value>
                        <Frequency>0.1</Frequency>
                        <InputUnits>
                            <Name>PA</Name>
                        </InputUnits>
                        <OutputUnits>
                            <Name>COUNTS</Name>
                        </OutputUnits>
                    </InstrumentSensitivity>
                </Response>
            </Channel>
            <Channel code="BDF" locationCode="" startDate="2017-10-12T00:00:00" endDate="2018-02-21T00:00:00">
                <Sensor>
                    <Description>I50GB ASCENSION ISLAND UK INFRASONIC ARRAY</Description>
                </Sensor>
                <Latitude>-7.932500</Latitude>
                <Longitude>-14.357200</Longitude>
                <Elevation>218</Elevation>
                <Depth>0</Depth>
                <Azimuth>0</Azimuth>
                <Dip>0</Dip>
                <SampleRate>20</SampleRate>
                <Response>
                    <InstrumentSensitivity>
                        <Value>10526.3</Value>
                        <Frequency>0.1</Frequency>
                        <InputUnits>
                            <Name>PA</Name>
                        </InputUnits>
                        <OutputUnits>
                            <Name>COUNTS</Name>
                        </OutputUnits>
                    </InstrumentSensitivity>
                </Response>
            </Channel>
            <Channel code="BDF" locationCode="" startDate="2018-02-22T00:00:00" endDate="2050-12-31T23:59:59">
                <Sensor>
                    <Description>I50GB ASCENSION ISLAND UK INFRASONIC ARRAY</Description>
                </Sensor>
                <Latitude>-7.932500</Latitude>
                <Longitude>-14.357200</Longitude>
                <Elevation>222.9</Elevation>
                <Depth>0</Depth>
                <Azimuth>0</Azimuth>
                <Dip>0</Dip>
                <SampleRate>20</SampleRate>
                <Response>
                    <InstrumentSensitivity>
                        <Value>10526.3</Value>
                        <Frequency>0.1</Frequency>
                        <InputUnits>
                            <Name>PA</Name>
                        </InputUnits>
                        <OutputUnits>
                            <Name>COUNTS</Name>
                        </OutputUnits>
                    </InstrumentSensitivity>
                </Response>
            </Channel>
        </Station>
        <Station code="I50H8" startDate="2017-10-12T00:00:00" endDate="2050-12-31T23:59:59">
            <Latitude>-7.951150</Latitude>
            <Longitude>-14.374116</Longitude>
            <Elevation>0.189252</Elevation>
            <Site>
                <Name>I50GB ASCENSION ISLAND UK INFRASONIC ARRAY H8</Name>
            </Site>
            <Channel code="BDF" locationCode="" startDate="2018-05-02T00:00:00" endDate="2050-12-31T23:59:59">
                <Sensor>
                    <Description>I50GB ASCENSION ISLAND UK INFRASONIC ARRAY</Description>
                </Sensor>
                <Latitude>-7.951150</Latitude>
                <Longitude>-14.374116</Longitude>
                <Elevation>0.189252</Elevation>
                <Depth>0</Depth>
                <Azimuth>0</Azimuth>
                <Dip>0</Dip>
                <SampleRate>20</SampleRate>
                <Response>
                    <InstrumentSensitivity>
                        <Value>10485.8</Value>
                        <Frequency>0.1</Frequency>
                        <InputUnits>
                            <Name>PA</Name>
                        </InputUnits>
                        <OutputUnits>
                            <Name>COUNTS</Name>
                        </OutputUnits>
                    </InstrumentSensitivity>
                </Response>
            </Channel>
            <Channel code="BDF" locationCode="" startDate="2017-10-12T00:00:00" endDate="2018-05-02T00:00:00">
                <Sensor>
                    <Description>I50GB ASCENSION ISLAND UK INFRASONIC ARRAY</Description>
                </Sensor>
                <Latitude>-7.951130</Latitude>
                <Longitude>-14.374090</Longitude>
                <Elevation>0.1923</Elevation>
                <Depth>0</Depth>
                <Azimuth>0</Azimuth>
                <Dip>0</Dip>
                <SampleRate>20</SampleRate>
                <Response>
                    <InstrumentSensitivity>
                        <Value>10485.8</Value>
                        <Frequency>0.1</Frequency>
                        <InputUnits>
                            <Name>PA</Name>
                        </InputUnits>
                        <OutputUnits>
                            <Name>COUNTS</Name>
                        </OutputUnits>
                    </InstrumentSensitivity>
                </Response>
            </Channel>
            <Channel code="BDF" locationCode="" startDate="2017-10-12T00:00:00" endDate="2018-02-21T00:00:00">
                <Sensor>
                    <Description>I50GB ASCENSION ISLAND UK INFRASONIC ARRAY</Description>
                </Sensor>
                <Latitude>-7.951100</Latitude>
                <Longitude>-14.374100</Longitude>
                <Elevation>192.3</Elevation>
                <Depth>0</Depth>
                <Azimuth>0</Azimuth>
                <Dip>0</Dip>
                <SampleRate>20</SampleRate>
                <Response>
                    <InstrumentSensitivity>
                        <Value>10526.3</Value>
                        <Frequency>0.1</Frequency>
                        <InputUnits>
                            <Name>PA</Name>
                        </InputUnits>
                        <OutputUnits>
                            <Name>COUNTS</Name>
                        </OutputUnits>
                    </InstrumentSensitivity>
                </Response>
            </Channel>
            <Channel code="BDF" locationCode="" startDate="2018-02-22T00:00:00" endDate="2050-12-31T23:59:59">
                <Sensor>
                    <Description>I50GB ASCENSION ISLAND UK INFRASONIC ARRAY</Description>
                </Sensor>
                <Latitude>-7.951200</Latitude>
                <Longitude>-14.374100</Longitude>
                <Elevation>189.3</Elevation>
                <Depth>0</Depth>
                <Azimuth>0</Azimuth>
                <Dip>0</Dip>
                <SampleRate>20</SampleRate>
                <Response>
                    <InstrumentSensitivity>
                        <Value>10526.3</Value>
                        <Frequency>0.1</Frequency>
                        <InputUnits>
                            <Name>PA</Name>
                        </InputUnits>
                        <OutputUnits>
                            <Name>COUNTS</Name>
                        </OutputUnits>
                    </InstrumentSensitivity>
                </Response>
            </Channel>
        </Station>
        <Station code="I50L1" startDate="2005-04-14T15:28:02" endDate="2017-10-11T00:00:00">
            <Latitude>-7.937740</Latitude>
            <Longitude>-14.375170</Longitude>
            <Elevation>0.18862</Elevation>
            <Site>
                <Name>I50GB L1</Name>
            </Site>
            <Channel code="BDF" locationCode="" startDate="2005-04-14T15:28:02" endDate="2017-10-11T00:00:00">
                <Sensor>
                    <Description>I50GB</Description>
                </Sensor>
                <Latitude>-7.937740</Latitude>
                <Longitude>-14.375170</Longitude>
                <Elevation>0.18862</Elevation>
                <Depth>0</Depth>
                <Azimuth>0</Azimuth>
                <Dip>0</Dip>
                <SampleRate>20</SampleRate>
                <Response>
                    <InstrumentSensitivity>
                        <Value>10485.8</Value>
                        <Frequency>0.1</Frequency>
                        <InputUnits>
                            <Name>PA</Name>
                        </InputUnits>
                        <OutputUnits>
                            <Name>COUNTS</Name>
                        </OutputUnits>
                    </InstrumentSensitivity>
                </Response>
            </Channel>
        </Station>
        <Station code="I50L2" startDate="2005-04-14T15:28:02" endDate="2017-10-11T00:00:00">
            <Latitude>-7.931900</Latitude>
            <Longitude>-14.382040</Longitude>
            <Elevation>0.14727</Elevation>
            <Site>
                <Name>I50GB L2</Name>
            </Site>
            <Channel code="BDF" locationCode="" startDate="2005-04-14T15:28:02" endDate="2017-10-11T00:00:00">
                <Sensor>
                    <Description>I50GB</Description>
                </Sensor>
                <Latitude>-7.931900</Latitude>
                <Longitude>-14.382040</Longitude>
                <Elevation>0.14727</Elevation>
                <Depth>0</Depth>
                <Azimuth>0</Azimuth>
                <Dip>0</Dip>
                <SampleRate>20</SampleRate>
                <Response>
                    <InstrumentSensitivity>
                        <Value>10485.8</Value>
                        <Frequency>0.1</Frequency>
                        <InputUnits>
                            <Name>PA</Name>
                        </InputUnits>
                        <OutputUnits>
                            <Name>COUNTS</Name>
                        </OutputUnits>
                    </InstrumentSensitivity>
                </Response>
            </Channel>
        </Station>
        <Station code="I50L3" startDate="2005-04-14T15:28:02" endDate="2017-10-11T00:00:00">
            <Latitude>-7.932500</Latitude>
            <Longitude>-14.357210</Longitude>
            <Elevation>0.21797</Elevation>
            <Site>
                <Name>I50GB L3</Name>
            </Site>
            <Channel code="BDF" locationCode="" startDate="2005-04-14T15:28:02" endDate="2017-10-11T00:00:00">
                <Sensor>
                    <Description>I50GB</Description>
                </Sensor>
                <Latitude>-7.932500</Latitude>
                <Longitude>-14.357210</Longitude>
                <Elevation>0.21797</Elevation>
                <Depth>0</Depth>
                <Azimuth>0</Azimuth>
                <Dip>0</Dip>
                <SampleRate>20</SampleRate>
                <Response>
                    <InstrumentSensitivity>
                        <Value>10485.8</Value>
                        <Frequency>0.1</Frequency>
                        <InputUnits>
                            <Name>PA</Name>
                        </InputUnits>
                        <OutputUnits>
                            <Name>COUNTS</Name>
                        </OutputUnits>
                    </InstrumentSensitivity>
                </Response>
            </Channel>
        </Station>
        <Station code="I50L4" startDate="2005-04-14T15:28:02" endDate="2017-10-11T00:00:00">
            <Latitude>-7.951130</Latitude>
            <Longitude>-14.374090</Longitude>
            <Elevation>0.1923</Elevation>
            <Site>
                <Name>I50GB L4</Name>
            </Site>
            <Channel code="BDF" locationCode="" startDate="2005-04-14T15:28:02" endDate="2017-10-11T00:00:00">
                <Sensor>
                    <Description>I50GB</Description>
                </Sensor>
                <Latitude>-7.951130</Latitude>
                <Longitude>-14.374090</Longitude>
                <Elevation>0.1923</Elevation>
                <Depth>0</Depth>
                <Azimuth>0</Azimuth>
                <Dip>0</Dip>
                <SampleRate>20</SampleRate>
                <Response>
                    <InstrumentSensitivity>
                        <Value>10485.8</Value>
                        <Frequency>0.1</Frequency>
                        <InputUnits>
                            <Name>PA</Name>
                        </InputUnits>
                        <OutputUnits>
                            <Name>COUNTS</Name>
                        </OutputUnits>
                    </InstrumentSensitivity>
                </Response>
            </Channel>
        </Station>
    </Network>
</FDSNStationXML>
